<results>
  <row>
    <data column="Configuration">root,</data>
    <data column="Measured Value">1200</data>
  </row>
  <row>
    <data column="Configuration">root,KeepAlive,FollowSymLinks,</data>
    <data column="Measured Value">2100</data>
  </row>
  <row>
    <data column="Configuration">root,KeepAlive,EnableSendfile,ExtendedStatus,InMemory,</data>
    <data column="Measured Value">2310</data>
  </row>
  <row>
    <data column="Configuration">root,EnableSendfile,AccessLog,InMemory,</data>
    <data column="Measured Value">1260</data>
  </row>
  <row>
    <data column="Configuration">root,EnableSendfile,AccessLog,ExtendedStatus,InMemory,</data>
    <data column="Measured Value">1140</data>
  </row>
  <row>
    <data column="Configuration">root,KeepAlive,EnableSendfile,AccessLog,InMemory,</data>
    <data column="Measured Value">2100</data>
  </row>
  <row>
    <data column="Configuration">root,KeepAlive,EnableSendfile,AccessLog,ExtendedStatus,InMemory,</data>
    <data column="Measured Value">1980</data>
  </row>
  <row>
    <data column="Configuration">root,HostnameLookups,EnableSendfile,InMemory,</data>
    <data column="Measured Value">1110</data>
  </row>
  <row>
    <data column="Configuration">root,HostnameLookups,KeepAlive,EnableSendfile,InMemory,</data>
    <data column="Measured Value">2160</data>
  </row>
  <row>
    <data column="Configuration">root,HostnameLookups,EnableSendfile,AccessLog,InMemory,</data>
    <data column="Measured Value">990</data>
  </row>
  <row>
    <data column="Configuration">root,HostnameLookups,KeepAlive,EnableSendfile,AccessLog,InMemory,</data>
    <data column="Measured Value">1890</data>
  </row>
  <row>
    <data column="Configuration">root,HostnameLookups,EnableSendfile,ExtendedStatus,InMemory,</data>
    <data column="Measured Value">1020</data>
  </row>
  <row>
    <data column="Configuration">root,FollowSymLinks,AccessLog,</data>
    <data column="Measured Value">1020</data>
  </row>
  <row>
    <data column="Configuration">root,HostnameLookups,EnableSendfile,AccessLog,ExtendedStatus,InMemory,</data>
    <data column="Measured Value">960</data>
  </row>
  <row>
    <data column="Configuration">root,HostnameLookups,KeepAlive,EnableSendfile,ExtendedStatus,InMemory,</data>
    <data column="Measured Value">2160</data>
  </row>
  <row>
    <data column="Configuration">root,HostnameLookups,KeepAlive,EnableSendfile,AccessLog,ExtendedStatus,InMemory,</data>
    <data column="Measured Value">1860</data>
  </row>
  <row>
    <data column="Configuration">root,EnableSendfile,FollowSymLinks,InMemory,</data>
    <data column="Measured Value">1470</data>
  </row>
  <row>
    <data column="Configuration">root,KeepAlive,EnableSendfile,FollowSymLinks,InMemory,</data>
    <data column="Measured Value">2640</data>
  </row>
  <row>
    <data column="Configuration">root,EnableSendfile,FollowSymLinks,ExtendedStatus,InMemory,</data>
    <data column="Measured Value">1380</data>
  </row>
  <row>
    <data column="Configuration">root,KeepAlive,EnableSendfile,FollowSymLinks,ExtendedStatus,InMemory,</data>
    <data column="Measured Value">2430</data>
  </row>
  <row>
    <data column="Configuration">root,HostnameLookups,EnableSendfile,FollowSymLinks,InMemory,</data>
    <data column="Measured Value">1140</data>
  </row>
  <row>
    <data column="Configuration">root,HostnameLookups,EnableSendfile,FollowSymLinks,ExtendedStatus,InMemory,</data>
    <data column="Measured Value">1080</data>
  </row>
  <row>
    <data column="Configuration">root,HostnameLookups,KeepAlive,EnableSendfile,FollowSymLinks,InMemory,</data>
    <data column="Measured Value">2340</data>
  </row>
  <row>
    <data column="Configuration">root,KeepAlive,FollowSymLinks,AccessLog,</data>
    <data column="Measured Value">1830</data>
  </row>
  <row>
    <data column="Configuration">root,HostnameLookups,KeepAlive,EnableSendfile,FollowSymLinks,ExtendedStatus,InMemory,</data>
    <data column="Measured Value">2190</data>
  </row>
  <row>
    <data column="Configuration">root,EnableSendfile,FollowSymLinks,AccessLog,InMemory,</data>
    <data column="Measured Value">1260</data>
  </row>
  <row>
    <data column="Configuration">root,KeepAlive,EnableSendfile,FollowSymLinks,AccessLog,InMemory,</data>
    <data column="Measured Value">2190</data>
  </row>
  <row>
    <data column="Configuration">root,HostnameLookups,EnableSendfile,FollowSymLinks,AccessLog,InMemory,</data>
    <data column="Measured Value">1020</data>
  </row>
  <row>
    <data column="Configuration">root,HostnameLookups,KeepAlive,EnableSendfile,FollowSymLinks,AccessLog,InMemory,</data>
    <data column="Measured Value">2100</data>
  </row>
  <row>
    <data column="Configuration">root,EnableSendfile,FollowSymLinks,AccessLog,ExtendedStatus,InMemory,</data>
    <data column="Measured Value">1230</data>
  </row>
  <row>
    <data column="Configuration">root,HostnameLookups,EnableSendfile,FollowSymLinks,AccessLog,ExtendedStatus,InMemory,</data>
    <data column="Measured Value">990</data>
  </row>
  <row>
    <data column="Configuration">root,KeepAlive,EnableSendfile,FollowSymLinks,AccessLog,ExtendedStatus,InMemory,</data>
    <data column="Measured Value">2070</data>
  </row>
  <row>
    <data column="Configuration">root,HostnameLookups,KeepAlive,EnableSendfile,FollowSymLinks,AccessLog,ExtendedStatus,InMemory,</data>
    <data column="Measured Value">1860</data>
  </row>
  <row>
    <data column="Configuration">root,Handle,</data>
    <data column="Measured Value">1230</data>
  </row>
  <row>
    <data column="Configuration">root,FollowSymLinks,ExtendedStatus,</data>
    <data column="Measured Value">1140</data>
  </row>
  <row>
    <data column="Configuration">root,ExtendedStatus,Handle,</data>
    <data column="Measured Value">1080</data>
  </row>
  <row>
    <data column="Configuration">root,AccessLog,Handle,</data>
    <data column="Measured Value">1050</data>
  </row>
  <row>
    <data column="Configuration">root,AccessLog,ExtendedStatus,Handle,</data>
    <data column="Measured Value">1080</data>
  </row>
  <row>
    <data column="Configuration">root,FollowSymLinks,Handle,</data>
    <data column="Measured Value">1260</data>
  </row>
  <row>
    <data column="Configuration">root,FollowSymLinks,AccessLog,Handle,</data>
    <data column="Measured Value">1200</data>
  </row>
  <row>
    <data column="Configuration">root,FollowSymLinks,ExtendedStatus,Handle,</data>
    <data column="Measured Value">1200</data>
  </row>
  <row>
    <data column="Configuration">root,FollowSymLinks,AccessLog,ExtendedStatus,Handle,</data>
    <data column="Measured Value">1050</data>
  </row>
  <row>
    <data column="Configuration">root,EnableSendfile,Handle,</data>
    <data column="Measured Value">1200</data>
  </row>
  <row>
    <data column="Configuration">root,EnableSendfile,ExtendedStatus,Handle,</data>
    <data column="Measured Value">1140</data>
  </row>
  <row>
    <data column="Configuration">root,EnableSendfile,FollowSymLinks,Handle,</data>
    <data column="Measured Value">1200</data>
  </row>
  <row>
    <data column="Configuration">root,FollowSymLinks,AccessLog,ExtendedStatus,</data>
    <data column="Measured Value">990</data>
  </row>
  <row>
    <data column="Configuration">root,EnableSendfile,FollowSymLinks,ExtendedStatus,Handle,</data>
    <data column="Measured Value">1230</data>
  </row>
  <row>
    <data column="Configuration">root,EnableSendfile,AccessLog,Handle,</data>
    <data column="Measured Value">1110</data>
  </row>
  <row>
    <data column="Configuration">root,EnableSendfile,FollowSymLinks,AccessLog,Handle,</data>
    <data column="Measured Value">1140</data>
  </row>
  <row>
    <data column="Configuration">root,EnableSendfile,AccessLog,ExtendedStatus,Handle,</data>
    <data column="Measured Value">1050</data>
  </row>
  <row>
    <data column="Configuration">root,EnableSendfile,FollowSymLinks,AccessLog,ExtendedStatus,Handle,</data>
    <data column="Measured Value">1110</data>
  </row>
  <row>
    <data column="Configuration">root,KeepAlive,Handle,</data>
    <data column="Measured Value">1200</data>
  </row>
  <row>
    <data column="Configuration">root,KeepAlive,ExtendedStatus,Handle,</data>
    <data column="Measured Value">1350</data>
  </row>
  <row>
    <data column="Configuration">root,KeepAlive,AccessLog,Handle,</data>
    <data column="Measured Value">1230</data>
  </row>
  <row>
    <data column="Configuration">root,KeepAlive,AccessLog,ExtendedStatus,Handle,</data>
    <data column="Measured Value">1260</data>
  </row>
  <row>
    <data column="Configuration">root,KeepAlive,EnableSendfile,Handle,</data>
    <data column="Measured Value">1290</data>
  </row>
  <row>
    <data column="Configuration">root,KeepAlive,FollowSymLinks,ExtendedStatus,</data>
    <data column="Measured Value">1950</data>
  </row>
  <row>
    <data column="Configuration">root,KeepAlive,EnableSendfile,AccessLog,Handle,</data>
    <data column="Measured Value">1020</data>
  </row>
  <row>
    <data column="Configuration">root,KeepAlive,EnableSendfile,ExtendedStatus,Handle,</data>
    <data column="Measured Value">1320</data>
  </row>
  <row>
    <data column="Configuration">root,KeepAlive,EnableSendfile,AccessLog,ExtendedStatus,Handle,</data>
    <data column="Measured Value">1230</data>
  </row>
  <row>
    <data column="Configuration">root,KeepAlive,FollowSymLinks,Handle,</data>
    <data column="Measured Value">1380</data>
  </row>
  <row>
    <data column="Configuration">root,KeepAlive,FollowSymLinks,ExtendedStatus,Handle,</data>
    <data column="Measured Value">1110</data>
  </row>
  <row>
    <data column="Configuration">root,KeepAlive,EnableSendfile,FollowSymLinks,Handle,</data>
    <data column="Measured Value">1200</data>
  </row>
  <row>
    <data column="Configuration">root,KeepAlive,EnableSendfile,FollowSymLinks,ExtendedStatus,Handle,</data>
    <data column="Measured Value">1110</data>
  </row>
  <row>
    <data column="Configuration">root,KeepAlive,FollowSymLinks,AccessLog,Handle,</data>
    <data column="Measured Value">1350</data>
  </row>
  <row>
    <data column="Configuration">root,KeepAlive,EnableSendfile,FollowSymLinks,AccessLog,Handle,</data>
    <data column="Measured Value">1200</data>
  </row>
  <row>
    <data column="Configuration">root,KeepAlive,FollowSymLinks,AccessLog,ExtendedStatus,Handle,</data>
    <data column="Measured Value">1230</data>
  </row>
  <row>
    <data column="Configuration">root,KeepAlive,FollowSymLinks,AccessLog,ExtendedStatus,</data>
    <data column="Measured Value">1740</data>
  </row>
  <row>
    <data column="Configuration">root,KeepAlive,EnableSendfile,FollowSymLinks,AccessLog,ExtendedStatus,Handle,</data>
    <data column="Measured Value">1170</data>
  </row>
  <row>
    <data column="Configuration">root,HostnameLookups,Handle,</data>
    <data column="Measured Value">990</data>
  </row>
  <row>
    <data column="Configuration">root,HostnameLookups,ExtendedStatus,Handle,</data>
    <data column="Measured Value">960</data>
  </row>
  <row>
    <data column="Configuration">root,HostnameLookups,AccessLog,Handle,</data>
    <data column="Measured Value">930</data>
  </row>
  <row>
    <data column="Configuration">root,HostnameLookups,AccessLog,ExtendedStatus,Handle,</data>
    <data column="Measured Value">870</data>
  </row>
  <row>
    <data column="Configuration">root,HostnameLookups,FollowSymLinks,Handle,</data>
    <data column="Measured Value">1020</data>
  </row>
  <row>
    <data column="Configuration">root,HostnameLookups,FollowSymLinks,AccessLog,Handle,</data>
    <data column="Measured Value">930</data>
  </row>
  <row>
    <data column="Configuration">root,HostnameLookups,FollowSymLinks,ExtendedStatus,Handle,</data>
    <data column="Measured Value">960</data>
  </row>
  <row>
    <data column="Configuration">root,HostnameLookups,FollowSymLinks,AccessLog,ExtendedStatus,Handle,</data>
    <data column="Measured Value">900</data>
  </row>
  <row>
    <data column="Configuration">root,HostnameLookups,KeepAlive,Handle,</data>
    <data column="Measured Value">1140</data>
  </row>
  <row>
    <data column="Configuration">root,EnableSendfile,</data>
    <data column="Measured Value">1320</data>
  </row>
  <row>
    <data column="Configuration">root,HostnameLookups,KeepAlive,ExtendedStatus,Handle,</data>
    <data column="Measured Value">1020</data>
  </row>
  <row>
    <data column="Configuration">root,HostnameLookups,KeepAlive,FollowSymLinks,Handle,</data>
    <data column="Measured Value">1320</data>
  </row>
  <row>
    <data column="Configuration">root,HostnameLookups,KeepAlive,FollowSymLinks,ExtendedStatus,Handle,</data>
    <data column="Measured Value">1170</data>
  </row>
  <row>
    <data column="Configuration">root,HostnameLookups,KeepAlive,AccessLog,Handle,</data>
    <data column="Measured Value">1200</data>
  </row>
  <row>
    <data column="Configuration">root,HostnameLookups,KeepAlive,FollowSymLinks,AccessLog,Handle,</data>
    <data column="Measured Value">1080</data>
  </row>
  <row>
    <data column="Configuration">root,HostnameLookups,KeepAlive,AccessLog,ExtendedStatus,Handle,</data>
    <data column="Measured Value">1140</data>
  </row>
  <row>
    <data column="Configuration">root,HostnameLookups,KeepAlive,FollowSymLinks,AccessLog,ExtendedStatus,Handle,</data>
    <data column="Measured Value">1500</data>
  </row>
  <row>
    <data column="Configuration">root,HostnameLookups,EnableSendfile,Handle,</data>
    <data column="Measured Value">990</data>
  </row>
  <row>
    <data column="Configuration">root,HostnameLookups,EnableSendfile,ExtendedStatus,Handle,</data>
    <data column="Measured Value">960</data>
  </row>
  <row>
    <data column="Configuration">root,HostnameLookups,EnableSendfile,AccessLog,Handle,</data>
    <data column="Measured Value">930</data>
  </row>
  <row>
    <data column="Configuration">root,KeepAlive,EnableSendfile,</data>
    <data column="Measured Value">2220</data>
  </row>
  <row>
    <data column="Configuration">root,HostnameLookups,EnableSendfile,AccessLog,ExtendedStatus,Handle,</data>
    <data column="Measured Value">870</data>
  </row>
  <row>
    <data column="Configuration">root,HostnameLookups,KeepAlive,EnableSendfile,Handle,</data>
    <data column="Measured Value">1170</data>
  </row>
  <row>
    <data column="Configuration">root,HostnameLookups,KeepAlive,EnableSendfile,AccessLog,Handle,</data>
    <data column="Measured Value">1080</data>
  </row>
  <row>
    <data column="Configuration">root,HostnameLookups,KeepAlive,EnableSendfile,ExtendedStatus,Handle,</data>
    <data column="Measured Value">1170</data>
  </row>
  <row>
    <data column="Configuration">root,HostnameLookups,KeepAlive,EnableSendfile,AccessLog,ExtendedStatus,Handle,</data>
    <data column="Measured Value">1470</data>
  </row>
  <row>
    <data column="Configuration">root,HostnameLookups,EnableSendfile,FollowSymLinks,Handle,</data>
    <data column="Measured Value">1050</data>
  </row>
  <row>
    <data column="Configuration">root,HostnameLookups,EnableSendfile,FollowSymLinks,ExtendedStatus,Handle,</data>
    <data column="Measured Value">990</data>
  </row>
  <row>
    <data column="Configuration">root,HostnameLookups,KeepAlive,EnableSendfile,FollowSymLinks,Handle,</data>
    <data column="Measured Value">1050</data>
  </row>
  <row>
    <data column="Configuration">root,HostnameLookups,KeepAlive,EnableSendfile,FollowSymLinks,ExtendedStatus,Handle,</data>
    <data column="Measured Value">1200</data>
  </row>
  <row>
    <data column="Configuration">root,HostnameLookups,EnableSendfile,FollowSymLinks,AccessLog,Handle,</data>
    <data column="Measured Value">930</data>
  </row>
  <row>
    <data column="Configuration">root,EnableSendfile,ExtendedStatus,</data>
    <data column="Measured Value">1230</data>
  </row>
  <row>
    <data column="Configuration">root,HostnameLookups,KeepAlive,EnableSendfile,FollowSymLinks,AccessLog,Handle,</data>
    <data column="Measured Value">1170</data>
  </row>
  <row>
    <data column="Configuration">root,HostnameLookups,EnableSendfile,FollowSymLinks,AccessLog,ExtendedStatus,Handle,</data>
    <data column="Measured Value">870</data>
  </row>
  <row>
    <data column="Configuration">root,HostnameLookups,KeepAlive,EnableSendfile,FollowSymLinks,AccessLog,ExtendedStatus,Handle,</data>
    <data column="Measured Value">870</data>
  </row>
  <row>
    <data column="Configuration">root,KeepAlive,</data>
    <data column="Measured Value">2040</data>
  </row>
  <row>
    <data column="Configuration">root,KeepAlive,EnableSendfile,ExtendedStatus,</data>
    <data column="Measured Value">2130</data>
  </row>
  <row>
    <data column="Configuration">root,EnableSendfile,FollowSymLinks,</data>
    <data column="Measured Value">1350</data>
  </row>
  <row>
    <data column="Configuration">root,EnableSendfile,FollowSymLinks,ExtendedStatus,</data>
    <data column="Measured Value">1170</data>
  </row>
  <row>
    <data column="Configuration">root,KeepAlive,EnableSendfile,FollowSymLinks,</data>
    <data column="Measured Value">2370</data>
  </row>
  <row>
    <data column="Configuration">root,KeepAlive,EnableSendfile,FollowSymLinks,ExtendedStatus,</data>
    <data column="Measured Value">2190</data>
  </row>
  <row>
    <data column="Configuration">root,EnableSendfile,AccessLog,</data>
    <data column="Measured Value">1170</data>
  </row>
  <row>
    <data column="Configuration">root,KeepAlive,EnableSendfile,AccessLog,</data>
    <data column="Measured Value">1980</data>
  </row>
  <row>
    <data column="Configuration">root,EnableSendfile,FollowSymLinks,AccessLog,</data>
    <data column="Measured Value">1200</data>
  </row>
  <row>
    <data column="Configuration">root,KeepAlive,EnableSendfile,FollowSymLinks,AccessLog,</data>
    <data column="Measured Value">2040</data>
  </row>
  <row>
    <data column="Configuration">root,EnableSendfile,AccessLog,ExtendedStatus,</data>
    <data column="Measured Value">1080</data>
  </row>
  <row>
    <data column="Configuration">root,ExtendedStatus,</data>
    <data column="Measured Value">1110</data>
  </row>
  <row>
    <data column="Configuration">root,EnableSendfile,FollowSymLinks,AccessLog,ExtendedStatus,</data>
    <data column="Measured Value">1110</data>
  </row>
  <row>
    <data column="Configuration">root,KeepAlive,EnableSendfile,AccessLog,ExtendedStatus,</data>
    <data column="Measured Value">1830</data>
  </row>
  <row>
    <data column="Configuration">root,KeepAlive,EnableSendfile,FollowSymLinks,AccessLog,ExtendedStatus,</data>
    <data column="Measured Value">1890</data>
  </row>
  <row>
    <data column="Configuration">root,HostnameLookups,</data>
    <data column="Measured Value">990</data>
  </row>
  <row>
    <data column="Configuration">root,HostnameLookups,KeepAlive,</data>
    <data column="Measured Value">1950</data>
  </row>
  <row>
    <data column="Configuration">root,HostnameLookups,ExtendedStatus,</data>
    <data column="Measured Value">900</data>
  </row>
  <row>
    <data column="Configuration">root,HostnameLookups,KeepAlive,ExtendedStatus,</data>
    <data column="Measured Value">1830</data>
  </row>
  <row>
    <data column="Configuration">root,HostnameLookups,AccessLog,</data>
    <data column="Measured Value">900</data>
  </row>
  <row>
    <data column="Configuration">root,HostnameLookups,AccessLog,ExtendedStatus,</data>
    <data column="Measured Value">840</data>
  </row>
  <row>
    <data column="Configuration">root,HostnameLookups,KeepAlive,AccessLog,</data>
    <data column="Measured Value">1710</data>
  </row>
  <row>
    <data column="Configuration">root,KeepAlive,ExtendedStatus,</data>
    <data column="Measured Value">1920</data>
  </row>
  <row>
    <data column="Configuration">root,HostnameLookups,KeepAlive,AccessLog,ExtendedStatus,</data>
    <data column="Measured Value">1620</data>
  </row>
  <row>
    <data column="Configuration">root,HostnameLookups,EnableSendfile,</data>
    <data column="Measured Value">1050</data>
  </row>
  <row>
    <data column="Configuration">root,HostnameLookups,KeepAlive,EnableSendfile,</data>
    <data column="Measured Value">2130</data>
  </row>
  <row>
    <data column="Configuration">root,HostnameLookups,EnableSendfile,AccessLog,</data>
    <data column="Measured Value">930</data>
  </row>
  <row>
    <data column="Configuration">root,HostnameLookups,KeepAlive,EnableSendfile,AccessLog,</data>
    <data column="Measured Value">1890</data>
  </row>
  <row>
    <data column="Configuration">root,HostnameLookups,EnableSendfile,ExtendedStatus,</data>
    <data column="Measured Value">960</data>
  </row>
  <row>
    <data column="Configuration">root,HostnameLookups,EnableSendfile,AccessLog,ExtendedStatus,</data>
    <data column="Measured Value">900</data>
  </row>
  <row>
    <data column="Configuration">root,HostnameLookups,KeepAlive,EnableSendfile,ExtendedStatus,</data>
    <data column="Measured Value">2010</data>
  </row>
  <row>
    <data column="Configuration">root,HostnameLookups,KeepAlive,EnableSendfile,AccessLog,ExtendedStatus,</data>
    <data column="Measured Value">1770</data>
  </row>
  <row>
    <data column="Configuration">root,HostnameLookups,FollowSymLinks,</data>
    <data column="Measured Value">960</data>
  </row>
  <row>
    <data column="Configuration">root,AccessLog,</data>
    <data column="Measured Value">1080</data>
  </row>
  <row>
    <data column="Configuration">root,HostnameLookups,KeepAlive,FollowSymLinks,</data>
    <data column="Measured Value">1950</data>
  </row>
  <row>
    <data column="Configuration">root,HostnameLookups,FollowSymLinks,ExtendedStatus,</data>
    <data column="Measured Value">930</data>
  </row>
  <row>
    <data column="Configuration">root,HostnameLookups,KeepAlive,FollowSymLinks,ExtendedStatus,</data>
    <data column="Measured Value">1890</data>
  </row>
  <row>
    <data column="Configuration">root,HostnameLookups,EnableSendfile,FollowSymLinks,</data>
    <data column="Measured Value">1080</data>
  </row>
  <row>
    <data column="Configuration">root,HostnameLookups,EnableSendfile,FollowSymLinks,ExtendedStatus,</data>
    <data column="Measured Value">990</data>
  </row>
  <row>
    <data column="Configuration">root,HostnameLookups,KeepAlive,EnableSendfile,FollowSymLinks,</data>
    <data column="Measured Value">2220</data>
  </row>
  <row>
    <data column="Configuration">root,HostnameLookups,KeepAlive,EnableSendfile,FollowSymLinks,ExtendedStatus,</data>
    <data column="Measured Value">2070</data>
  </row>
  <row>
    <data column="Configuration">root,HostnameLookups,FollowSymLinks,AccessLog,</data>
    <data column="Measured Value">900</data>
  </row>
  <row>
    <data column="Configuration">root,HostnameLookups,KeepAlive,FollowSymLinks,AccessLog,</data>
    <data column="Measured Value">1770</data>
  </row>
  <row>
    <data column="Configuration">root,HostnameLookups,EnableSendfile,FollowSymLinks,AccessLog,</data>
    <data column="Measured Value">960</data>
  </row>
  <row>
    <data column="Configuration">root,AccessLog,ExtendedStatus,</data>
    <data column="Measured Value">1020</data>
  </row>
  <row>
    <data column="Configuration">root,HostnameLookups,KeepAlive,EnableSendfile,FollowSymLinks,AccessLog,</data>
    <data column="Measured Value">1920</data>
  </row>
  <row>
    <data column="Configuration">root,HostnameLookups,FollowSymLinks,AccessLog,ExtendedStatus,</data>
    <data column="Measured Value">840</data>
  </row>
  <row>
    <data column="Configuration">root,HostnameLookups,EnableSendfile,FollowSymLinks,AccessLog,ExtendedStatus,</data>
    <data column="Measured Value">900</data>
  </row>
  <row>
    <data column="Configuration">root,HostnameLookups,KeepAlive,FollowSymLinks,AccessLog,ExtendedStatus,</data>
    <data column="Measured Value">1680</data>
  </row>
  <row>
    <data column="Configuration">root,HostnameLookups,KeepAlive,EnableSendfile,FollowSymLinks,AccessLog,ExtendedStatus,</data>
    <data column="Measured Value">1800</data>
  </row>
  <row>
    <data column="Configuration">root,InMemory,</data>
    <data column="Measured Value">1410</data>
  </row>
  <row>
    <data column="Configuration">root,KeepAlive,InMemory,</data>
    <data column="Measured Value">2490</data>
  </row>
  <row>
    <data column="Configuration">root,ExtendedStatus,InMemory,</data>
    <data column="Measured Value">1290</data>
  </row>
  <row>
    <data column="Configuration">root,KeepAlive,ExtendedStatus,InMemory,</data>
    <data column="Measured Value">2250</data>
  </row>
  <row>
    <data column="Configuration">root,AccessLog,InMemory,</data>
    <data column="Measured Value">1260</data>
  </row>
  <row>
    <data column="Configuration">root,KeepAlive,AccessLog,</data>
    <data column="Measured Value">1770</data>
  </row>
  <row>
    <data column="Configuration">root,AccessLog,ExtendedStatus,InMemory,</data>
    <data column="Measured Value">1140</data>
  </row>
  <row>
    <data column="Configuration">root,KeepAlive,AccessLog,InMemory,</data>
    <data column="Measured Value">2130</data>
  </row>
  <row>
    <data column="Configuration">root,KeepAlive,AccessLog,ExtendedStatus,InMemory,</data>
    <data column="Measured Value">1980</data>
  </row>
  <row>
    <data column="Configuration">root,FollowSymLinks,InMemory,</data>
    <data column="Measured Value">1410</data>
  </row>
  <row>
    <data column="Configuration">root,KeepAlive,FollowSymLinks,InMemory,</data>
    <data column="Measured Value">2400</data>
  </row>
  <row>
    <data column="Configuration">root,FollowSymLinks,AccessLog,InMemory,</data>
    <data column="Measured Value">1320</data>
  </row>
  <row>
    <data column="Configuration">root,KeepAlive,FollowSymLinks,AccessLog,InMemory,</data>
    <data column="Measured Value">2190</data>
  </row>
  <row>
    <data column="Configuration">root,FollowSymLinks,ExtendedStatus,InMemory,</data>
    <data column="Measured Value">1380</data>
  </row>
  <row>
    <data column="Configuration">root,FollowSymLinks,AccessLog,ExtendedStatus,InMemory,</data>
    <data column="Measured Value">1230</data>
  </row>
  <row>
    <data column="Configuration">root,KeepAlive,FollowSymLinks,ExtendedStatus,InMemory,</data>
    <data column="Measured Value">2430</data>
  </row>
  <row>
    <data column="Configuration">root,KeepAlive,AccessLog,ExtendedStatus,</data>
    <data column="Measured Value">1680</data>
  </row>
  <row>
    <data column="Configuration">root,KeepAlive,FollowSymLinks,AccessLog,ExtendedStatus,InMemory,</data>
    <data column="Measured Value">2100</data>
  </row>
  <row>
    <data column="Configuration">root,HostnameLookups,InMemory,</data>
    <data column="Measured Value">1110</data>
  </row>
  <row>
    <data column="Configuration">root,HostnameLookups,KeepAlive,InMemory,</data>
    <data column="Measured Value">2280</data>
  </row>
  <row>
    <data column="Configuration">root,HostnameLookups,ExtendedStatus,InMemory,</data>
    <data column="Measured Value">1020</data>
  </row>
  <row>
    <data column="Configuration">root,HostnameLookups,KeepAlive,ExtendedStatus,InMemory,</data>
    <data column="Measured Value">2160</data>
  </row>
  <row>
    <data column="Configuration">root,HostnameLookups,FollowSymLinks,InMemory,</data>
    <data column="Measured Value">1140</data>
  </row>
  <row>
    <data column="Configuration">root,HostnameLookups,FollowSymLinks,ExtendedStatus,InMemory,</data>
    <data column="Measured Value">1050</data>
  </row>
  <row>
    <data column="Configuration">root,HostnameLookups,KeepAlive,FollowSymLinks,InMemory,</data>
    <data column="Measured Value">2280</data>
  </row>
  <row>
    <data column="Configuration">root,HostnameLookups,KeepAlive,FollowSymLinks,ExtendedStatus,InMemory,</data>
    <data column="Measured Value">2190</data>
  </row>
  <row>
    <data column="Configuration">root,HostnameLookups,AccessLog,InMemory,</data>
    <data column="Measured Value">1020</data>
  </row>
  <row>
    <data column="Configuration">root,FollowSymLinks,</data>
    <data column="Measured Value">1200</data>
  </row>
  <row>
    <data column="Configuration">root,HostnameLookups,KeepAlive,AccessLog,InMemory,</data>
    <data column="Measured Value">1980</data>
  </row>
  <row>
    <data column="Configuration">root,HostnameLookups,FollowSymLinks,AccessLog,InMemory,</data>
    <data column="Measured Value">1020</data>
  </row>
  <row>
    <data column="Configuration">root,HostnameLookups,KeepAlive,FollowSymLinks,AccessLog,InMemory,</data>
    <data column="Measured Value">2070</data>
  </row>
  <row>
    <data column="Configuration">root,HostnameLookups,AccessLog,ExtendedStatus,InMemory,</data>
    <data column="Measured Value">930</data>
  </row>
  <row>
    <data column="Configuration">root,HostnameLookups,FollowSymLinks,AccessLog,ExtendedStatus,InMemory,</data>
    <data column="Measured Value">960</data>
  </row>
  <row>
    <data column="Configuration">root,HostnameLookups,KeepAlive,AccessLog,ExtendedStatus,InMemory,</data>
    <data column="Measured Value">1860</data>
  </row>
  <row>
    <data column="Configuration">root,HostnameLookups,KeepAlive,FollowSymLinks,AccessLog,ExtendedStatus,InMemory,</data>
    <data column="Measured Value">1920</data>
  </row>
  <row>
    <data column="Configuration">root,EnableSendfile,InMemory,</data>
    <data column="Measured Value">1410</data>
  </row>
  <row>
    <data column="Configuration">root,KeepAlive,EnableSendfile,InMemory,</data>
    <data column="Measured Value">2460</data>
  </row>
  <row>
    <data column="Configuration">root,EnableSendfile,ExtendedStatus,InMemory,</data>
    <data column="Measured Value">1320</data>
  </row>
</results>